[
  {
    "code": "605179",
    "name": "一鸣食品",
    "direction": "short",
    "buy_date": "2026-05-28",
    "buy_price": 15.18,
    "stop_loss": 16.282,
    "target": 14.358999999999998,
    "position_pct": 0.1,
    "score": 95,
    "middle": 13.398499999999999,
    "upper": 14.089249999999998,
    "lower": 12.707749999999999,
    "current_price": 13.02,
    "hold_days": 42
  },
  {
    "code": "605011",
    "name": "杭州热电",
    "direction": "short",
    "buy_date": "2026-06-24",
    "buy_price": 17.83,
    "stop_loss": 19.909,
    "target": 15.925999999999998,
    "position_pct": 0.1,
    "score": 92,
    "middle": 16.864,
    "upper": 18.124750000000002,
    "lower": 15.603250000000001,
    "current_price": 15.77,
    "hold_days": 15
  },
  {
    "code": "601799",
    "name": "星宇股份",
    "direction": "short",
    "buy_date": "2026-06-29",
    "buy_price": 97.91,
    "stop_loss": 118.71149999999997,
    "target": 87.17899999999999,
    "position_pct": 0.1,
    "score": 97,
    "middle": 107.40650000000001,
    "upper": 115.28675000000001,
    "lower": 99.52625,
    "current_price": 97.67,
    "hold_days": 10
  },
  {
    "code": "600373",
    "name": "中文传媒",
    "direction": "short",
    "buy_date": "2026-07-02",
    "buy_price": 6.74,
    "stop_loss": 7.301,
    "target": 6.279,
    "position_pct": 0.1,
    "score": 90,
    "middle": 7.097999999999999,
    "upper": 7.4137499999999985,
    "lower": 6.7822499999999994,
    "current_price": 6.73,
    "hold_days": 7
  },
  {
    "code": "600120",
    "name": "浙江东方",
    "direction": "long",
    "buy_date": "2026-07-09",
    "buy_price": 5.06,
    "stop_loss": 4.531499999999999,
    "target": 5.420999999999999,
    "position_pct": 0.1,
    "score": 97,
    "middle": 4.531499999999999,
    "upper": 4.802249999999999,
    "lower": 4.26075,
    "current_price": 5.06,
    "hold_days": 0
  }
]